[
  {
    "step": 0,
    "loss": 0.18514734506607056
  },
  {
    "step": 1,
    "loss": 0.0922250747680664
  },
  {
    "step": 2,
    "loss": 0.039333526045084
  },
  {
    "step": 3,
    "loss": 0.01856725476682186
  },
  {
    "step": 4,
    "loss": 0.014501198194921017
  },
  {
    "step": 5,
    "loss": 0.007015761453658342
  },
  {
    "step": 6,
    "loss": 0.0035173071082681417
  },
  {
    "step": 7,
    "loss": 0.003932442981749773
  },
  {
    "step": 8,
    "loss": 0.003386429976671934
  },
  {
    "step": 9,
    "loss": 0.002278905129060149
  }
]